{"id":0,"registry":{"0":{"submorphs":[],"scripts":[],"id":"9B2FFA9E-C245-4C49-B15D-8619909A01DD","shape":{"__isSmartRef__":true,"id":1},"grabbingEnabled":false,"droppingEnabled":false,"halosEnabled":true,"fixedWidth":true,"fixedHeight":false,"allowsInput":true,"_FontFamily":"Arial, sans-serif","registeredForMouseEvents":true,"_Position":{"__isSmartRef__":true,"id":8},"_MaxTextWidth":674.695652,"_MaxTextHeight":null,"textColor":{"__isSmartRef__":true,"id":4},"showsHalos":false,"_FontSize":14,"name":"MetaNote","partsBinMetaInfo":{"__isSmartRef__":true,"id":9},"textChunks":[{"__isSmartRef__":true,"id":24}],"charsReplaced":"lect","lastFindLoc":9,"prevScroll":[0,0],"renderContextTable":{"__isSmartRef__":true,"id":27},"eventHandler":{"__isSmartRef__":true,"id":28},"_Padding":{"__isSmartRef__":true,"id":29},"_ClipMode":"visible","derivationIds":[355,"1EB1674F-8BF2-419B-B054-86129ED70335","63698904-DC05-4341-A9B6-5CC4A219CD04","F6A714BA-4735-41ED-8A2A-45CB153FBDF8","CC31C8E9-B249-42F4-AA46-2C9654E56CE2","11108C6A-802C-41B7-A51C-DE1E483B68FC"],"_WhiteSpaceHandling":"pre-wrap","_MinTextWidth":674.695652,"_MinTextHeight":null,"isBeingDragged":false,"moved":true,"distanceToDragEvent":{"__isSmartRef__":true,"id":30},"_Rotation":0,"_Scale":1,"_Visible":true,"lastSearchString":"","lastSearchIndex":0,"searchHighlights":[],"isMetaNote":true,"__LivelyClassName__":"lively.morphic.Text","__SourceModuleName__":"Global.lively.morphic.TextCore"},"1":{"fill":null,"_Position":{"__isSmartRef__":true,"id":2},"_Extent":{"__isSmartRef__":true,"id":3},"_BorderWidth":0,"_BorderColor":{"__isSmartRef__":true,"id":4},"renderContextTable":{"__isSmartRef__":true,"id":5},"_ClipMode":"visible","_Padding":{"__isSmartRef__":true,"id":6},"_Fill":{"__isSmartRef__":true,"id":7},"_BorderRadius":0,"_Opacity":1,"_BorderStyle":"solid","_AppearanceStylingMode":false,"_BorderStylingMode":false,"__LivelyClassName__":"lively.morphic.Shapes.Rectangle","__SourceModuleName__":"Global.lively.morphic.Shapes"},"2":{"x":0,"y":0,"__LivelyClassName__":"Point","__SourceModuleName__":"Global.lively.morphic.Graphics"},"3":{"x":694.695652,"y":42,"__LivelyClassName__":"Point","__SourceModuleName__":"Global.lively.morphic.Graphics"},"4":{"r":0,"g":0,"b":0,"a":1,"__LivelyClassName__":"Color","__SourceModuleName__":"Global.lively.morphic.Graphics"},"5":{"init":"initHTML","appendShape":"renderHTML","setPosition":"setPositionHTML","setExtent":"setExtentHTML","setPadding":"setPaddingHTML","setFill":"setFillHTML","setBorderColor":"setBorderColorHTML","setBorderWidth":"setBorderWidthHTML","setStrokeOpacity":"setStrokeOpacityHTML","setBorderRadius":"setBorderRadiusHTML","setBorderStyle":"setBorderStyleHTML","setOpacity":"setOpacityHTML","setAppearanceStylingMode":"setAppearanceStylingModeHTML","setBorderStylingMode":"setBorderStylingModeHTML","getComputedBorderWidth":"getComputedBorderWidthHTML","getComputedExtent":"getComputedExtentHTML"},"6":{"x":10,"y":10,"width":0,"height":0,"__LivelyClassName__":"Rectangle","__SourceModuleName__":"Global.lively.morphic.Graphics"},"7":{"r":0.3137254901960784,"g":0.3137254901960784,"b":0.3137254901960784,"a":1,"__LivelyClassName__":"Color","__SourceModuleName__":"Global.lively.morphic.Graphics"},"8":{"x":0,"y":0,"__LivelyClassName__":"Point","__SourceModuleName__":"Global.lively.morphic.Graphics"},"9":{"partsSpaceName":"PartsBin/Jens","migrationLevel":4,"comment":"A meta note","partName":"MetaNote","changes":[{"__isSmartRef__":true,"id":10},{"__isSmartRef__":true,"id":12},{"__isSmartRef__":true,"id":14},{"__isSmartRef__":true,"id":16},{"__isSmartRef__":true,"id":18},{"__isSmartRef__":true,"id":20},{"__isSmartRef__":true,"id":22}],"revisionOnLoad":160159,"__LivelyClassName__":"lively.PartsBin.PartsBinMetaInfo","__SourceModuleName__":"Global.lively.PartsBin"},"10":{"date":{"__isSmartRef__":true,"id":11},"author":"robertkrahn","message":"text click was broken?","id":"9D065E14-9653-4B2A-9A2E-3AD84EBBC3E0"},"11":{"isSerializedDate":true,"string":"Sat Apr 21 2012 16:30:30 GMT+0200 (CEST)"},"12":{"date":{"__isSmartRef__":true,"id":13},"author":"undefined","message":"Set the inset as: this.setPadding(Rectangle.inset(4,2)).  This gives it a more pleasing appearance with a border, and also makes it easier to select near the bounds.","id":"BD5B0E4C-4830-4863-A013-35BB66D5AD6F"},"13":{"isSerializedDate":true,"string":"Mon Feb 27 2012 06:20:38 GMT+0100 (CET)"},"14":{"date":{"__isSmartRef__":true,"id":15},"author":"tessi","message":"TextBubble calls its disappear() function after showBubbleTime() milliseconds now","id":"0F4DE333-A551-4961-B29D-70270977EBEF"},"15":{"isSerializedDate":true,"string":"Sat Apr 21 2012 07:31:43 GMT+0200 (CEST)"},"16":{"date":{"__isSmartRef__":true,"id":17},"author":"tessi","message":"TextBubble calls its disappear() function after showBubbleTime() milliseconds now","id":"785D95BD-7858-43EB-90E6-A1C085E2F2B9"},"17":{"isSerializedDate":true,"string":"Sat Apr 21 2012 07:32:09 GMT+0200 (CEST)"},"18":{"date":{"__isSmartRef__":true,"id":19},"author":"timfelgentreff","message":"better text","id":"B904F9AC-6EA0-4A8A-83C9-AFC85AADC194"},"19":{"isSerializedDate":true,"string":"Tue May 08 2012 14:18:18 GMT+0200 (CEST)"},"20":{"date":{"__isSmartRef__":true,"id":21},"author":"jenslincke","message":"no comment","id":"7E5DD706-80B5-4C94-AE17-413CA78820C7"},"21":{"isSerializedDate":true,"string":"Wed Nov 28 2012 16:32:29 GMT+0100 (CET)"},"22":{"date":{"__isSmartRef__":true,"id":23},"author":"jenslincke","message":"no comment","id":"4F9B7E2E-ACC1-4CFA-B2E7-D8F58F9053B3"},"23":{"isSerializedDate":true,"string":"Wed Nov 28 2012 16:32:33 GMT+0100 (CET)"},"24":{"style":{"__isSmartRef__":true,"id":25},"morph":{"__isSmartRef__":true,"id":0},"chunkOwner":{"__isSmartRef__":true,"id":0},"storedString":"META: ...","_id":"_19900","__LivelyClassName__":"lively.morphic.TextChunk","__SourceModuleName__":"Global.lively.morphic.TextCore"},"25":{"color":{"__isSmartRef__":true,"id":26},"__LivelyClassName__":"lively.morphic.TextEmphasis","__SourceModuleName__":"Global.lively.morphic.TextCore"},"26":{"r":1,"g":0.56,"b":0,"a":1,"__LivelyClassName__":"Color","__SourceModuleName__":"Global.lively.morphic.Graphics"},"27":{"replaceRenderContext":"replaceRenderContextHTML","init":"initHTML","append":"appendHTML","remove":"removeHTML","removeMorph":"removeMorphHTML","onRenderFinished":"onRenderFinishedHTML","triggerEvent":"triggerEventHTML","setTransform":"setTransformHTML","setPosition":"setPositionHTML","setRotation":"setRotationHTML","setExtent":"setExtentHTML","setScale":"setScaleHTML","setVisible":"setVisibleHTML","adjustOrigin":"adjustOriginHTML","setPivotPoint":"setPivotPointHTML","setClipMode":"setClipModeHTML","showsVerticalScrollBar":"showsVerticalScrollBarHTML","showsHorizontalScrollBar":"showsHorizontalScrollBarHTML","getScrollBarExtent":"getScrollBarExtentHTML","setHandStyle":"setHandStyleHTML","setPointerEvents":"setPointerEventsHTML","setToolTip":"setToolTipHTML","focus":"focusHTML","blur":"blurHTML","setFocusable":"setFocusableHTML","setStyleSheet":"setStyleSheetHTML","setStyleClassNames":"setStyleClassNamesHTML","setStyleId":"setStyleIdHTML","updateText":"updateTextHTML","setTextExtent":"setTextExtentHTML","setMaxTextWidth":"setMaxTextWidthHTML","setMaxTextHeight":"setMaxTextHeightHTML","setMinTextWidth":"setMinTextWidthHTML","setMinTextHeight":"setMinTextHeightHTML","getTextExtent":"getTextExtentHTML","getTextString":"getTextStringHTML","ignoreTextEvents":"ignoreTextEventsHTML","unignoreTextEvents":"unignoreTextEventsHTML","enableTextEvents":"enableTextEventsHTML","setFontFamily":"setFontFamilyHTML","setFontSize":"setFontSizeHTML","setTextColor":"setTextColorHTML","setFontWeight":"setFontWeightHTML","setFontStyle":"setFontStyleHTML","setTextDecoration":"setTextDecorationHTML","setPadding":"setPaddingHTML","setAlign":"setAlignHTML","setVerticalAlign":"setVerticalAlignHTML","setDisplay":"setDisplayHTML","setWhiteSpaceHandling":"setWhiteSpaceHandlingHTML","setWordBreak":"setWordBreakHTML","focusMorph":"focusMorphHTML","setInputAllowed":"setInputAllowedHTML"},"28":{"morph":{"__isSmartRef__":true,"id":0},"__LivelyClassName__":"lively.morphic.EventHandler","__SourceModuleName__":"Global.lively.morphic.Events"},"29":{"x":5,"y":5,"width":0,"height":0,"__LivelyClassName__":"Rectangle","__SourceModuleName__":"Global.lively.morphic.Graphics"},"30":{"x":472,"y":-17.666666666666657,"__LivelyClassName__":"Point","__SourceModuleName__":"Global.lively.morphic.Graphics"},"isSimplifiedRegistry":true}}